django_shared_schema_tenants-0.1.0.dist-info/DESCRIPTION.rst
django_shared_schema_tenants-0.1.0.dist-info/METADATA
django_shared_schema_tenants-0.1.0.dist-info/RECORD
django_shared_schema_tenants-0.1.0.dist-info/WHEEL
django_shared_schema_tenants-0.1.0.dist-info/metadata.json
django_shared_schema_tenants-0.1.0.dist-info/top_level.txt
shared_schema_tenants/__init__.py
shared_schema_tenants/admin.py
shared_schema_tenants/apps.py
shared_schema_tenants/auth_backends.py
shared_schema_tenants/exceptions.py
shared_schema_tenants/managers.py
shared_schema_tenants/middleware.py
shared_schema_tenants/mixins.py
shared_schema_tenants/models.py
shared_schema_tenants/permissions.py
shared_schema_tenants/serializers.py
shared_schema_tenants/settings.py
shared_schema_tenants/urls.py
shared_schema_tenants/utils.py
shared_schema_tenants/validators.py
shared_schema_tenants/views.py
shared_schema_tenants/helpers/__init__.py
shared_schema_tenants/helpers/tenant_extra_data.py
shared_schema_tenants/helpers/tenant_json_field.py
shared_schema_tenants/helpers/tenant_relationships.py
shared_schema_tenants/helpers/tenant_settings.py
shared_schema_tenants/helpers/tenants.py
shared_schema_tenants/management/__init__.py
shared_schema_tenants/management/commands/__init__.py
shared_schema_tenants/management/commands/createtenant.py
shared_schema_tenants/migrations/0001_initial.py
shared_schema_tenants/migrations/__init__.py
