Metadata-Version: 2.0
Name: django-shared-schema-tenants
Version: 0.1.0
Summary: A lib to help in the creation of shared schema multi tenants applications without suffering
Home-page: https://github.com/hugobessa/django-shared-schema-tenants
Author: Hugo Bessa
Author-email: hugo@bessa.me
License: MIT
Keywords: django-shared-schema-tenants
Platform: UNKNOWN
Classifier: Development Status :: 3 - Alpha
Classifier: Framework :: Django
Classifier: Framework :: Django :: 1.10
Classifier: Framework :: Django :: 1.11
Classifier: Intended Audience :: Developers
Classifier: License :: OSI Approved :: BSD License
Classifier: Natural Language :: English
Classifier: Programming Language :: Python :: 2
Classifier: Programming Language :: Python :: 2.7
Classifier: Programming Language :: Python :: 3
Classifier: Programming Language :: Python :: 3.5
Classifier: Programming Language :: Python :: 3.6
Requires-Dist: django-model-utils (>=2.0)
